{
  "title" : "列表2",
  "image" : [ {
    "imageName" : "c8b9b875-b4a3-42fe-84ee-8c5c9f60ca04.png"
  } ],
  "date" : "05/03/2025",
  "content" : "Confiamos en que las autoridades de ambos países trabajen para encontrar una mayor cooperación y soluciones duraderas aunque, por supuesto, seguimos atentos a lo que pudiera decirse en marzo”, señaló la gobernadora del banco central.\n\nAnalistas han advertido que los aranceles podrían sumir a México en una recesión y desencadenar una “estanflación”, es decir, una inflación elevada, un crecimiento estancado y un desempleo elevado."
}